{
  "metadata": {
    "name": "maxxpainn",
    "version": "0.1.0",
    "spec": "0.1.0",
    "description": "MaxxPainn is a free-to-mint token protocol on Solana inspired by XEN Network, promoting fair launch, no presale, no VCs, pure community grind."
  },
  "instructions": [
    {
      "name": "claim_rank",
      "discriminator": [
        48,
        155,
        49,
        204,
        4,
        160,
        113,
        182
      ],
      "accounts": [
        {
          "name": "signer",
          "writable": true,
          "signer": true
        },
        {
          "name": "main_config",
          "pda": {
            "seeds": [
              {
                "kind": "const",
                "value": [
                  109,
                  97,
                  105,
                  110,
                  95,
                  99,
                  111,
                  110,
                  102,
                  105,
                  103
                ]
              }
            ]
          }
        },
        {
          "name": "protocol_state",
          "writable": true,
          "pda": {
            "seeds": [
              {
                "kind": "const",
                "value": [
                  112,
                  114,
                  111,
                  116,
                  111,
                  99,
                  111,
                  108,
                  95,
                  115,
                  116,
                  97,
                  116,
                  101
                ]
              }
            ]
          }
        },
        {
          "name": "rank_info",
          "writable": true,
          "pda": {
            "seeds": [
              {
                "kind": "const",
                "value": [
                  114,
                  97,
                  110,
                  107,
                  95,
                  105,
                  110,
                  102,
                  111
                ]
              },
              {
                "kind": "account",
                "path": "signer"
              }
            ]
          }
        },
        {
          "name": "rank_difficulty",
          "writable": true
        },
        {
          "name": "system_program",
          "address": "11111111111111111111111111111111"
        }
      ],
      "args": [
        {
          "name": "wait_period_days",
          "type": "u16"
        },
        {
          "name": "clan_id",
          "type": "u64"
        },
        {
          "name": "referrer",
          "type": "u64"
        },
        {
          "name": "rank_difficulty_bump",
          "type": "u8"
        }
      ]
    },
    {
      "name": "claim_tokens",
      "discriminator": [
        108,
        216,
        210,
        231,
        0,
        212,
        42,
        64
      ],
      "accounts": [
        {
          "name": "signer",
          "writable": true,
          "signer": true
        },
        {
          "name": "mint_authority",
          "pda": {
            "seeds": [
              {
                "kind": "const",
                "value": [
                  109,
                  105,
                  110,
                  116,
                  95,
                  97,
                  117,
                  116,
                  104,
                  111,
                  114,
                  105,
                  116,
                  121
                ]
              }
            ]
          }
        },
        {
          "name": "mint",
          "writable": true,
          "pda": {
            "seeds": [
              {
                "kind": "const",
                "value": [
                  109,
                  105,
                  110,
                  116
                ]
              }
            ]
          }
        },
        {
          "name": "rank_info",
          "writable": true,
          "pda": {
            "seeds": [
              {
                "kind": "const",
                "value": [
                  114,
                  97,
                  110,
                  107,
                  95,
                  105,
                  110,
                  102,
                  111
                ]
              },
              {
                "kind": "account",
                "path": "token_claimer"
              }
            ]
          }
        },
        {
          "name": "close_authority",
          "pda": {
            "seeds": [
              {
                "kind": "const",
                "value": [
                  99,
                  108,
                  111,
                  115,
                  101,
                  95,
                  97,
                  117,
                  116,
                  104,
                  111,
                  114,
                  105,
                  116,
                  121
                ]
              }
            ]
          }
        },
        {
          "name": "token_claimer",
          "writable": true
        },
        {
          "name": "token_claimer_ata",
          "writable": true,
          "pda": {
            "seeds": [
              {
                "kind": "account",
                "path": "token_claimer"
              },
              {
                "kind": "account",
                "path": "token_program"
              },
              {
                "kind": "account",
                "path": "mint"
              }
            ],
            "program": {
              "kind": "const",
              "value": [
                140,
                151,
                37,
                143,
                78,
                36,
                137,
                241,
                187,
                61,
                16,
                41,
                20,
                142,
                13,
                131,
                11,
                90,
                19,
                153,
                218,
                255,
                16,
                132,
                4,
                142,
                123,
                216,
                219,
                233,
                248,
                89
              ]
            }
          }
        },
        {
          "name": "main_config",
          "pda": {
            "seeds": [
              {
                "kind": "const",
                "value": [
                  109,
                  97,
                  105,
                  110,
                  95,
                  99,
                  111,
                  110,
                  102,
                  105,
                  103
                ]
              }
            ]
          }
        },
        {
          "name": "protocol_state",
          "writable": true,
          "pda": {
            "seeds": [
              {
                "kind": "const",
                "value": [
                  112,
                  114,
                  111,
                  116,
                  111,
                  99,
                  111,
                  108,
                  95,
                  115,
                  116,
                  97,
                  116,
                  101
                ]
              }
            ]
          }
        },
        {
          "name": "system_program",
          "address": "11111111111111111111111111111111"
        },
        {
          "name": "associated_token_program",
          "address": "ATokenGPvbdGVxr1b2hvZbsiqW5xWH25efTNsLJA8knL"
        },
        {
          "name": "token_program",
          "address": "TokenkegQfeZyiNwAJbNbGKPFXCWuBvf9Ss623VQ5DA"
        }
      ],
      "args": []
    },
    {
      "name": "close_rank",
      "discriminator": [
        126,
        127,
        91,
        142,
        122,
        165,
        143,
        176
      ],
      "accounts": [
        {
          "name": "signer",
          "writable": true,
          "signer": true
        },
        {
          "name": "main_config",
          "pda": {
            "seeds": [
              {
                "kind": "const",
                "value": [
                  109,
                  97,
                  105,
                  110,
                  95,
                  99,
                  111,
                  110,
                  102,
                  105,
                  103
                ]
              }
            ]
          }
        },
        {
          "name": "treasury",
          "writable": true
        },
        {
          "name": "rank_owner",
          "writable": true
        },
        {
          "name": "rank_info",
          "writable": true,
          "pda": {
            "seeds": [
              {
                "kind": "const",
                "value": [
                  114,
                  97,
                  110,
                  107,
                  95,
                  105,
                  110,
                  102,
                  111
                ]
              },
              {
                "kind": "account",
                "path": "rank_owner"
              }
            ]
          }
        },
        {
          "name": "system_program",
          "address": "11111111111111111111111111111111"
        }
      ],
      "args": []
    },
    {
      "name": "close_rank_difficulty",
      "discriminator": [
        112,
        101,
        28,
        59,
        229,
        118,
        32,
        47
      ],
      "accounts": [
        {
          "name": "signer",
          "writable": true,
          "signer": true
        },
        {
          "name": "main_config",
          "pda": {
            "seeds": [
              {
                "kind": "const",
                "value": [
                  109,
                  97,
                  105,
                  110,
                  95,
                  99,
                  111,
                  110,
                  102,
                  105,
                  103
                ]
              }
            ]
          }
        },
        {
          "name": "treasury",
          "writable": true
        },
        {
          "name": "rank_difficulty_owner"
        },
        {
          "name": "rank_difficulty",
          "docs": [
            "We manually validate seeds here to ensure security."
          ],
          "writable": true,
          "pda": {
            "seeds": [
              {
                "kind": "const",
                "value": [
                  114,
                  97,
                  110,
                  107,
                  95,
                  100,
                  105,
                  102,
                  102,
                  105,
                  99,
                  117,
                  108,
                  116,
                  121
                ]
              },
              {
                "kind": "account",
                "path": "rank_difficulty_owner"
              }
            ]
          }
        },
        {
          "name": "system_program",
          "address": "11111111111111111111111111111111"
        }
      ],
      "args": []
    },
    {
      "name": "close_stake_account",
      "discriminator": [
        246,
        236,
        59,
        167,
        115,
        135,
        122,
        12
      ],
      "accounts": [
        {
          "name": "signer",
          "writable": true,
          "signer": true
        },
        {
          "name": "main_config",
          "pda": {
            "seeds": [
              {
                "kind": "const",
                "value": [
                  109,
                  97,
                  105,
                  110,
                  95,
                  99,
                  111,
                  110,
                  102,
                  105,
                  103
                ]
              }
            ]
          }
        },
        {
          "name": "treasury",
          "writable": true
        },
        {
          "name": "stake_owner",
          "writable": true
        },
        {
          "name": "stake_info",
          "writable": true,
          "pda": {
            "seeds": [
              {
                "kind": "const",
                "value": [
                  115,
                  116,
                  97,
                  107,
                  101,
                  95,
                  105,
                  110,
                  102,
                  111
                ]
              },
              {
                "kind": "account",
                "path": "stake_owner"
              }
            ]
          }
        },
        {
          "name": "system_program",
          "address": "11111111111111111111111111111111"
        }
      ],
      "args": []
    },
    {
      "name": "initialize_main_config",
      "discriminator": [
        163,
        30,
        48,
        175,
        133,
        116,
        243,
        83
      ],
      "accounts": [
        {
          "name": "signer",
          "writable": true,
          "signer": true
        },
        {
          "name": "main_config",
          "writable": true,
          "pda": {
            "seeds": [
              {
                "kind": "const",
                "value": [
                  109,
                  97,
                  105,
                  110,
                  95,
                  99,
                  111,
                  110,
                  102,
                  105,
                  103
                ]
              }
            ]
          }
        },
        {
          "name": "protocol_state",
          "writable": true,
          "pda": {
            "seeds": [
              {
                "kind": "const",
                "value": [
                  112,
                  114,
                  111,
                  116,
                  111,
                  99,
                  111,
                  108,
                  95,
                  115,
                  116,
                  97,
                  116,
                  101
                ]
              }
            ]
          }
        },
        {
          "name": "system_program",
          "address": "11111111111111111111111111111111"
        }
      ],
      "args": [
        {
          "name": "authority",
          "type": "pubkey"
        },
        {
          "name": "treasury",
          "type": "pubkey"
        },
        {
          "name": "can_mint",
          "type": "bool"
        },
        {
          "name": "max_token_supply",
          "type": "u64"
        },
        {
          "name": "rank_difficulty_base_fee",
          "type": "u64"
        },
        {
          "name": "rank_difficulty_scale_factor",
          "type": {
            "array": [
              "u8",
              2
            ]
          }
        },
        {
          "name": "staking_enabled",
          "type": "bool"
        },
        {
          "name": "staking_min_yield_bps",
          "type": "u64"
        },
        {
          "name": "staking_max_yield_bps",
          "type": "u64"
        },
        {
          "name": "staking_min_term_days",
          "type": "u64"
        },
        {
          "name": "staking_max_term_days",
          "type": "u64"
        },
        {
          "name": "early_unstake_penalty_bps",
          "type": "u64"
        }
      ]
    },
    {
      "name": "initialize_token",
      "discriminator": [
        38,
        209,
        150,
        50,
        190,
        117,
        16,
        54
      ],
      "accounts": [
        {
          "name": "signer",
          "writable": true,
          "signer": true
        },
        {
          "name": "mint_authority",
          "pda": {
            "seeds": [
              {
                "kind": "const",
                "value": [
                  109,
                  105,
                  110,
                  116,
                  95,
                  97,
                  117,
                  116,
                  104,
                  111,
                  114,
                  105,
                  116,
                  121
                ]
              }
            ]
          }
        },
        {
          "name": "mint",
          "writable": true,
          "pda": {
            "seeds": [
              {
                "kind": "const",
                "value": [
                  109,
                  105,
                  110,
                  116
                ]
              }
            ]
          }
        },
        {
          "name": "metadata",
          "writable": true
        },
        {
          "name": "token_metadata_program",
          "address": "metaqbxxUerdq28cj1RbAWkYQm3ybzjb6a8bt518x1s"
        },
        {
          "name": "system_program",
          "address": "11111111111111111111111111111111"
        },
        {
          "name": "token_program",
          "address": "TokenkegQfeZyiNwAJbNbGKPFXCWuBvf9Ss623VQ5DA"
        },
        {
          "name": "rent",
          "address": "SysvarRent111111111111111111111111111111111"
        }
      ],
      "args": [
        {
          "name": "name",
          "type": "string"
        },
        {
          "name": "symbol",
          "type": "string"
        },
        {
          "name": "uri",
          "type": "string"
        }
      ]
    },
    {
      "name": "stake",
      "discriminator": [
        206,
        176,
        202,
        18,
        200,
        209,
        179,
        108
      ],
      "accounts": [
        {
          "name": "signer",
          "writable": true,
          "signer": true
        },
        {
          "name": "main_config",
          "pda": {
            "seeds": [
              {
                "kind": "const",
                "value": [
                  109,
                  97,
                  105,
                  110,
                  95,
                  99,
                  111,
                  110,
                  102,
                  105,
                  103
                ]
              }
            ]
          }
        },
        {
          "name": "mint",
          "pda": {
            "seeds": [
              {
                "kind": "const",
                "value": [
                  109,
                  105,
                  110,
                  116
                ]
              }
            ]
          }
        },
        {
          "name": "staking_vault",
          "writable": true,
          "pda": {
            "seeds": [
              {
                "kind": "const",
                "value": [
                  115,
                  116,
                  97,
                  107,
                  105,
                  110,
                  103,
                  95,
                  118,
                  97,
                  117,
                  108,
                  116
                ]
              },
              {
                "kind": "account",
                "path": "mint"
              }
            ]
          }
        },
        {
          "name": "stake_info",
          "writable": true,
          "pda": {
            "seeds": [
              {
                "kind": "const",
                "value": [
                  115,
                  116,
                  97,
                  107,
                  101,
                  95,
                  105,
                  110,
                  102,
                  111
                ]
              },
              {
                "kind": "account",
                "path": "signer"
              }
            ]
          }
        },
        {
          "name": "user_token_account",
          "writable": true,
          "pda": {
            "seeds": [
              {
                "kind": "account",
                "path": "signer"
              },
              {
                "kind": "const",
                "value": [
                  6,
                  221,
                  246,
                  225,
                  215,
                  101,
                  161,
                  147,
                  217,
                  203,
                  225,
                  70,
                  206,
                  235,
                  121,
                  172,
                  28,
                  180,
                  133,
                  237,
                  95,
                  91,
                  55,
                  145,
                  58,
                  140,
                  245,
                  133,
                  126,
                  255,
                  0,
                  169
                ]
              },
              {
                "kind": "account",
                "path": "mint"
              }
            ],
            "program": {
              "kind": "const",
              "value": [
                140,
                151,
                37,
                143,
                78,
                36,
                137,
                241,
                187,
                61,
                16,
                41,
                20,
                142,
                13,
                131,
                11,
                90,
                19,
                153,
                218,
                255,
                16,
                132,
                4,
                142,
                123,
                216,
                219,
                233,
                248,
                89
              ]
            }
          }
        },
        {
          "name": "system_program",
          "address": "11111111111111111111111111111111"
        },
        {
          "name": "token_program",
          "address": "TokenkegQfeZyiNwAJbNbGKPFXCWuBvf9Ss623VQ5DA"
        },
        {
          "name": "associated_token_program",
          "address": "ATokenGPvbdGVxr1b2hvZbsiqW5xWH25efTNsLJA8knL"
        }
      ],
      "args": [
        {
          "name": "amount",
          "type": "u64"
        },
        {
          "name": "term_days",
          "type": "u64"
        }
      ]
    },
    {
      "name": "test_algos",
      "discriminator": [
        194,
        175,
        55,
        135,
        67,
        100,
        121,
        119
      ],
      "accounts": [
        {
          "name": "signer",
          "writable": true,
          "signer": true
        },
        {
          "name": "main_config",
          "pda": {
            "seeds": [
              {
                "kind": "const",
                "value": [
                  109,
                  97,
                  105,
                  110,
                  95,
                  99,
                  111,
                  110,
                  102,
                  105,
                  103
                ]
              }
            ]
          }
        },
        {
          "name": "protocol_state",
          "writable": true,
          "pda": {
            "seeds": [
              {
                "kind": "const",
                "value": [
                  112,
                  114,
                  111,
                  116,
                  111,
                  99,
                  111,
                  108,
                  95,
                  115,
                  116,
                  97,
                  116,
                  101
                ]
              }
            ]
          }
        },
        {
          "name": "rank_info",
          "writable": true,
          "pda": {
            "seeds": [
              {
                "kind": "const",
                "value": [
                  114,
                  97,
                  110,
                  107,
                  95,
                  105,
                  110,
                  102,
                  111
                ]
              },
              {
                "kind": "account",
                "path": "signer"
              }
            ]
          }
        },
        {
          "name": "rank_difficulty",
          "writable": true
        },
        {
          "name": "system_program",
          "address": "11111111111111111111111111111111"
        }
      ],
      "args": [
        {
          "name": "rank_no",
          "type": "u64"
        },
        {
          "name": "rank_difficulty_bump",
          "type": "u8"
        }
      ]
    },
    {
      "name": "unstake",
      "discriminator": [
        90,
        95,
        107,
        42,
        205,
        124,
        50,
        225
      ],
      "accounts": [
        {
          "name": "signer",
          "writable": true,
          "signer": true
        },
        {
          "name": "main_config",
          "pda": {
            "seeds": [
              {
                "kind": "const",
                "value": [
                  109,
                  97,
                  105,
                  110,
                  95,
                  99,
                  111,
                  110,
                  102,
                  105,
                  103
                ]
              }
            ]
          }
        },
        {
          "name": "mint",
          "writable": true,
          "pda": {
            "seeds": [
              {
                "kind": "const",
                "value": [
                  109,
                  105,
                  110,
                  116
                ]
              }
            ]
          }
        },
        {
          "name": "mint_authority",
          "pda": {
            "seeds": [
              {
                "kind": "const",
                "value": [
                  109,
                  105,
                  110,
                  116,
                  95,
                  97,
                  117,
                  116,
                  104,
                  111,
                  114,
                  105,
                  116,
                  121
                ]
              }
            ]
          }
        },
        {
          "name": "staking_vault",
          "writable": true,
          "pda": {
            "seeds": [
              {
                "kind": "const",
                "value": [
                  115,
                  116,
                  97,
                  107,
                  105,
                  110,
                  103,
                  95,
                  118,
                  97,
                  117,
                  108,
                  116
                ]
              },
              {
                "kind": "account",
                "path": "mint"
              }
            ]
          }
        },
        {
          "name": "stake_info",
          "writable": true,
          "pda": {
            "seeds": [
              {
                "kind": "const",
                "value": [
                  115,
                  116,
                  97,
                  107,
                  101,
                  95,
                  105,
                  110,
                  102,
                  111
                ]
              },
              {
                "kind": "account",
                "path": "signer"
              }
            ]
          }
        },
        {
          "name": "protocol_state",
          "writable": true,
          "pda": {
            "seeds": [
              {
                "kind": "const",
                "value": [
                  112,
                  114,
                  111,
                  116,
                  111,
                  99,
                  111,
                  108,
                  95,
                  115,
                  116,
                  97,
                  116,
                  101
                ]
              }
            ]
          }
        },
        {
          "name": "user_token_account",
          "writable": true,
          "pda": {
            "seeds": [
              {
                "kind": "account",
                "path": "signer"
              },
              {
                "kind": "const",
                "value": [
                  6,
                  221,
                  246,
                  225,
                  215,
                  101,
                  161,
                  147,
                  217,
                  203,
                  225,
                  70,
                  206,
                  235,
                  121,
                  172,
                  28,
                  180,
                  133,
                  237,
                  95,
                  91,
                  55,
                  145,
                  58,
                  140,
                  245,
                  133,
                  126,
                  255,
                  0,
                  169
                ]
              },
              {
                "kind": "account",
                "path": "mint"
              }
            ],
            "program": {
              "kind": "const",
              "value": [
                140,
                151,
                37,
                143,
                78,
                36,
                137,
                241,
                187,
                61,
                16,
                41,
                20,
                142,
                13,
                131,
                11,
                90,
                19,
                153,
                218,
                255,
                16,
                132,
                4,
                142,
                123,
                216,
                219,
                233,
                248,
                89
              ]
            }
          }
        },
        {
          "name": "system_program",
          "address": "11111111111111111111111111111111"
        },
        {
          "name": "associated_token_program",
          "address": "ATokenGPvbdGVxr1b2hvZbsiqW5xWH25efTNsLJA8knL"
        },
        {
          "name": "token_program",
          "address": "TokenkegQfeZyiNwAJbNbGKPFXCWuBvf9Ss623VQ5DA"
        }
      ],
      "args": [
        {
          "name": "is_emergency",
          "type": "bool"
        }
      ]
    },
    {
      "name": "update_authority",
      "discriminator": [
        32,
        46,
        64,
        28,
        149,
        75,
        243,
        88
      ],
      "accounts": [
        {
          "name": "main_config",
          "writable": true,
          "pda": {
            "seeds": [
              {
                "kind": "const",
                "value": [
                  109,
                  97,
                  105,
                  110,
                  95,
                  99,
                  111,
                  110,
                  102,
                  105,
                  103
                ]
              }
            ]
          }
        },
        {
          "name": "authority",
          "writable": true,
          "signer": true,
          "relations": [
            "main_config"
          ]
        }
      ],
      "args": [
        {
          "name": "authority",
          "type": "pubkey"
        }
      ]
    },
    {
      "name": "update_main_config",
      "discriminator": [
        104,
        147,
        158,
        17,
        207,
        118,
        131,
        220
      ],
      "accounts": [
        {
          "name": "main_config",
          "writable": true,
          "pda": {
            "seeds": [
              {
                "kind": "const",
                "value": [
                  109,
                  97,
                  105,
                  110,
                  95,
                  99,
                  111,
                  110,
                  102,
                  105,
                  103
                ]
              }
            ]
          }
        },
        {
          "name": "authority",
          "writable": true,
          "signer": true,
          "relations": [
            "main_config"
          ]
        }
      ],
      "args": [
        {
          "name": "treasury",
          "type": {
            "option": "pubkey"
          }
        },
        {
          "name": "can_mint",
          "type": {
            "option": "bool"
          }
        },
        {
          "name": "max_token_supply",
          "type": {
            "option": "u64"
          }
        },
        {
          "name": "claim_rank_min_wait_period_days",
          "type": {
            "option": "u8"
          }
        },
        {
          "name": "claim_rank_max_wait_period_days",
          "type": {
            "option": "u16"
          }
        },
        {
          "name": "rank_difficulty_base_fee",
          "type": {
            "option": "u64"
          }
        },
        {
          "name": "rank_difficulty_scale_factor",
          "type": {
            "option": {
              "array": [
                "u8",
                2
              ]
            }
          }
        },
        {
          "name": "staking_enabled",
          "type": {
            "option": "bool"
          }
        },
        {
          "name": "staking_min_yield_bps",
          "type": {
            "option": "u64"
          }
        },
        {
          "name": "staking_max_yield_bps",
          "type": {
            "option": "u64"
          }
        },
        {
          "name": "staking_min_term_days",
          "type": {
            "option": "u64"
          }
        },
        {
          "name": "staking_max_term_days",
          "type": {
            "option": "u64"
          }
        },
        {
          "name": "early_unstake_penalty_bps",
          "type": {
            "option": "u64"
          }
        }
      ]
    }
  ],
  "accounts": [
    {
      "name": "MainConfig",
      "discriminator": [
        58,
        191,
        119,
        63,
        62,
        107,
        101,
        66
      ]
    },
    {
      "name": "ProtocolState",
      "discriminator": [
        33,
        51,
        173,
        134,
        35,
        140,
        195,
        248
      ]
    },
    {
      "name": "RankInfo",
      "discriminator": [
        10,
        30,
        49,
        153,
        207,
        198,
        115,
        204
      ]
    },
    {
      "name": "StakeInfo",
      "discriminator": [
        66,
        62,
        68,
        70,
        108,
        179,
        183,
        235
      ]
    }
  ],
  "events": [
    {
      "name": "ClaimRankLog",
      "discriminator": [
        53,
        8,
        179,
        123,
        140,
        176,
        145,
        157
      ]
    },
    {
      "name": "StakeEvent",
      "discriminator": [
        226,
        134,
        188,
        173,
        19,
        33,
        75,
        175
      ]
    },
    {
      "name": "TokenClaim",
      "discriminator": [
        236,
        193,
        3,
        110,
        204,
        114,
        67,
        39
      ]
    },
    {
      "name": "UnstakeEvent",
      "discriminator": [
        162,
        104,
        137,
        228,
        81,
        3,
        79,
        197
      ]
    }
  ],
  "errors": [
    {
      "code": 6000,
      "name": "NonPositiveInput",
      "msg": "Input must be greater than zero"
    },
    {
      "code": 6001,
      "name": "MathOverflow",
      "msg": "A math overflow during calculation"
    },
    {
      "code": 6002,
      "name": "DivisionByZero",
      "msg": "Division by zero"
    },
    {
      "code": 6003,
      "name": "ConversionFailure",
      "msg": "Conversion to u64 failed (too large)"
    },
    {
      "code": 6004,
      "name": "MathError",
      "msg": "Math error"
    },
    {
      "code": 6005,
      "name": "DivisionError",
      "msg": "An errr occured during division operation"
    },
    {
      "code": 6006,
      "name": "InvalidAuthority",
      "msg": "The authority must be a valid pubkey"
    },
    {
      "code": 6007,
      "name": "InvalidTreasury",
      "msg": "The treasury address must be a valid pubkey"
    },
    {
      "code": 6008,
      "name": "AccountAlreadyInitialized",
      "msg": "The account is already initialized"
    },
    {
      "code": 6009,
      "name": "CannotCloseActiveAccount",
      "msg": "Active user rank info acount cannot be closed"
    },
    {
      "code": 6010,
      "name": "UserNotPermitted",
      "msg": "User is not permitted to run operation"
    },
    {
      "code": 6011,
      "name": "AccountNotInitialized",
      "msg": "The account is not initialized"
    },
    {
      "code": 6012,
      "name": "MintDisabled",
      "msg": "Minting is not enabled"
    },
    {
      "code": 6013,
      "name": "InvalidAccountToClose",
      "msg": "The account to be closed is invalid"
    },
    {
      "code": 6014,
      "name": "InvalidPdaAccount",
      "msg": "The provided pda account is invalid"
    },
    {
      "code": 6015,
      "name": "TokenAlreadyClaimed",
      "msg": "The tokens already claimed"
    },
    {
      "code": 6016,
      "name": "NotRankOwner",
      "msg": "The user isn't the rank owner"
    },
    {
      "code": 6017,
      "name": "InvalidUserRank",
      "msg": "Invalid user rank number"
    },
    {
      "code": 6018,
      "name": "WaitPeriodNotOver",
      "msg": "Wait period not over"
    },
    {
      "code": 6019,
      "name": "MinWaitPeriodError",
      "msg": "Wait period lower the minimum period"
    },
    {
      "code": 6020,
      "name": "MaxWaitPeriodError",
      "msg": "Wait period exceeds maximum period"
    },
    {
      "code": 6021,
      "name": "InvalidStakingTerms",
      "msg": "Invalid staking term rane"
    },
    {
      "code": 6022,
      "name": "InvalidStakingYieldBps",
      "msg": "Invalid staking yield range"
    },
    {
      "code": 6023,
      "name": "InvalidEarlyUnstakePenalty",
      "msg": "Early unstake penalty cannot be 0"
    },
    {
      "code": 6024,
      "name": "InvalidMaxTokenSupply",
      "msg": "Max token supply cannot be 0"
    }
  ],
  "types": [
    {
      "name": "ClaimRankLog",
      "type": {
        "kind": "struct",
        "fields": [
          {
            "name": "owner",
            "type": "pubkey"
          },
          {
            "name": "rank_no",
            "type": "u64"
          },
          {
            "name": "clan_id",
            "type": "u64"
          },
          {
            "name": "referrer",
            "type": "u64"
          },
          {
            "name": "created_at",
            "type": "i64"
          },
          {
            "name": "wait_period_days",
            "type": "u16"
          },
          {
            "name": "rank_difficulty_lamports",
            "type": "u64"
          },
          {
            "name": "global_rank",
            "type": "u64"
          }
        ]
      }
    },
    {
      "name": "MainConfig",
      "type": {
        "kind": "struct",
        "fields": [
          {
            "name": "authority",
            "type": "pubkey"
          },
          {
            "name": "treasury",
            "type": "pubkey"
          },
          {
            "name": "can_mint",
            "type": "bool"
          },
          {
            "name": "is_initialized",
            "type": "bool"
          },
          {
            "name": "max_token_supply",
            "type": "u64"
          },
          {
            "name": "claim_rank_min_wait_period_days",
            "type": "u8"
          },
          {
            "name": "claim_rank_max_wait_period_days",
            "type": "u16"
          },
          {
            "name": "rank_difficulty_base_fee_lamports",
            "docs": [
              "base fee in lamports (1 SOL = 1_000_000_000 lamports)"
            ],
            "type": "u64"
          },
          {
            "name": "rank_difficulty_scale_factor",
            "docs": [
              "initial growth rate multiplier for the fee curve (controls steepness, in ratio)",
              "this is a decimal in fixed point math",
              "example: 0.5 = [5,10] = 5/10 = 0.5"
            ],
            "type": {
              "array": [
                "u8",
                2
              ]
            }
          },
          {
            "name": "staking_enabled",
            "type": "bool"
          },
          {
            "name": "staking_min_yield_bps",
            "type": "u64"
          },
          {
            "name": "staking_max_yield_bps",
            "type": "u64"
          },
          {
            "name": "staking_min_term_days",
            "type": "u64"
          },
          {
            "name": "staking_max_term_days",
            "type": "u64"
          },
          {
            "name": "early_unstake_penalty_bps",
            "type": "u64"
          }
        ]
      }
    },
    {
      "name": "ProtocolState",
      "type": {
        "kind": "struct",
        "fields": [
          {
            "name": "global_rank",
            "type": "u64"
          },
          {
            "name": "total_tokens_minted",
            "type": "u64"
          }
        ]
      }
    },
    {
      "name": "RankInfo",
      "type": {
        "kind": "struct",
        "fields": [
          {
            "name": "owner",
            "type": "pubkey"
          },
          {
            "name": "rank_no",
            "type": "u64"
          },
          {
            "name": "created_at",
            "type": "i64"
          },
          {
            "name": "minted_at",
            "type": "i64"
          },
          {
            "name": "wait_period_secs",
            "type": "u64"
          },
          {
            "name": "clan_id",
            "type": "u64"
          },
          {
            "name": "has_minted",
            "type": "bool"
          },
          {
            "name": "amount_minted",
            "type": "u64"
          },
          {
            "name": "referrer",
            "type": "u64"
          }
        ]
      }
    },
    {
      "name": "StakeEvent",
      "type": {
        "kind": "struct",
        "fields": [
          {
            "name": "owner",
            "type": "pubkey"
          },
          {
            "name": "amount",
            "type": "u64"
          },
          {
            "name": "term_days",
            "type": "u64"
          },
          {
            "name": "start_time",
            "type": "i64"
          },
          {
            "name": "end_time",
            "type": "i64"
          }
        ]
      }
    },
    {
      "name": "StakeInfo",
      "type": {
        "kind": "struct",
        "fields": [
          {
            "name": "owner",
            "type": "pubkey"
          },
          {
            "name": "amount",
            "type": "u64"
          },
          {
            "name": "start_time",
            "type": "i64"
          },
          {
            "name": "end_time",
            "type": "i64"
          },
          {
            "name": "term_days",
            "type": "u64"
          },
          {
            "name": "pending_rewards",
            "type": "u64"
          },
          {
            "name": "is_active",
            "type": "bool"
          }
        ]
      }
    },
    {
      "name": "TokenClaim",
      "type": {
        "kind": "struct",
        "fields": [
          {
            "name": "rank_no",
            "type": "u64"
          },
          {
            "name": "account",
            "type": "pubkey"
          },
          {
            "name": "amount",
            "type": "u64"
          },
          {
            "name": "minted_at",
            "type": "i64"
          },
          {
            "name": "global_rank",
            "type": "u64"
          }
        ]
      }
    },
    {
      "name": "UnstakeEvent",
      "type": {
        "kind": "struct",
        "fields": [
          {
            "name": "owner",
            "type": "pubkey"
          },
          {
            "name": "amount",
            "type": "u64"
          },
          {
            "name": "reward",
            "type": "u64"
          },
          {
            "name": "is_emergency",
            "type": "bool"
          }
        ]
      }
    }
  ],
  "adddress": ""
}